alibabacloud_oss_v2/__init__.py
alibabacloud_oss_v2/_client.py
alibabacloud_oss_v2/_version.py
alibabacloud_oss_v2/checkpoint.py
alibabacloud_oss_v2/client.py
alibabacloud_oss_v2/config.py
alibabacloud_oss_v2/copier.py
alibabacloud_oss_v2/crc.py
alibabacloud_oss_v2/defaults.py
alibabacloud_oss_v2/downloader.py
alibabacloud_oss_v2/encryption_client.py
alibabacloud_oss_v2/endpoints.py
alibabacloud_oss_v2/exceptions.py
alibabacloud_oss_v2/filelike.py
alibabacloud_oss_v2/io_utils.py
alibabacloud_oss_v2/paginator.py
alibabacloud_oss_v2/presigner.py
alibabacloud_oss_v2/progress.py
alibabacloud_oss_v2/serde.py
alibabacloud_oss_v2/serde_utils.py
alibabacloud_oss_v2/types.py
alibabacloud_oss_v2/uploader.py
alibabacloud_oss_v2/utils.py
alibabacloud_oss_v2/validation.py
alibabacloud_oss_v2/aio/__init__.py
alibabacloud_oss_v2/aio/_aioclient.py
alibabacloud_oss_v2/aio/aio_utils.py
alibabacloud_oss_v2/aio/client.py
alibabacloud_oss_v2/aio/operations/__init__.py
alibabacloud_oss_v2/aio/operations/bucket_basic.py
alibabacloud_oss_v2/aio/operations/bucket_tags.py
alibabacloud_oss_v2/aio/operations/object_basic.py
alibabacloud_oss_v2/aio/operations/region.py
alibabacloud_oss_v2/aio/operations/service.py
alibabacloud_oss_v2/aio/transport/__init__.py
alibabacloud_oss_v2/aio/transport/aiohttp_client.py
alibabacloud_oss_v2/credentials/__init__.py
alibabacloud_oss_v2/credentials/provider_impl.py
alibabacloud_oss_v2/crypto/__init__.py
alibabacloud_oss_v2/crypto/aes_ctr.py
alibabacloud_oss_v2/crypto/aes_ctr_cipher.py
alibabacloud_oss_v2/crypto/cipher.py
alibabacloud_oss_v2/crypto/master_rsa_cipher.py
alibabacloud_oss_v2/crypto/types.py
alibabacloud_oss_v2/models/__init__.py
alibabacloud_oss_v2/models/access_point.py
alibabacloud_oss_v2/models/access_point_public_access_block.py
alibabacloud_oss_v2/models/bucket_access_monitor.py
alibabacloud_oss_v2/models/bucket_archive_direct_read.py
alibabacloud_oss_v2/models/bucket_basic.py
alibabacloud_oss_v2/models/bucket_cname.py
alibabacloud_oss_v2-1.2.2.dist-info/LICENSE
alibabacloud_oss_v2-1.2.2.dist-info/METADATA
alibabacloud_oss_v2-1.2.2.dist-info/WHEEL
alibabacloud_oss_v2-1.2.2.dist-info/top_level.txt
alibabacloud_oss_v2-1.2.2.dist-info/RECORD
