Metadata-Version: 2.1
Name: alibabacloud-oss-v2
Version: 1.2.2
Summary: Alibaba Cloud OSS (Object Storage Service) SDK V2 for Python
Home-page: https://github.com/aliyun/alibabacloud-oss-python-sdk-v2
Author: Alibaba Cloud OSS SDK
Author-email: sdk-team@alibabacloud.com
License: Apache License 2.0
Keywords: alibabacloud,oss
Platform: any
Classifier: Development Status :: 4 - Beta
Classifier: Programming Language :: Python
Classifier: Programming Language :: Python :: 3 :: Only
Classifier: Programming Language :: Python :: 3
Classifier: Programming Language :: Python :: 3.8
Classifier: Programming Language :: Python :: 3.9
Classifier: Programming Language :: Python :: 3.10
Classifier: Programming Language :: Python :: 3.11
Classifier: Programming Language :: Python :: 3.12
Classifier: License :: OSI Approved :: Apache Software License
Requires-Python: >=3.8
License-File: LICENSE
Requires-Dist: crcmod-plus (>=2.1.0)
Requires-Dist: pycryptodome (>=3.4.7)
Requires-Dist: requests (>=2.18.4)
